tobikodata/__init__.py
tobikodata/pypi_reserve/__init__.py
tobikodata/pypi_reserve/sqlmesh_enterprise/README.md
tobikodata/pypi_reserve/sqlmesh_enterprise/__init__.py
tobikodata/pypi_reserve/sqlmesh_enterprise/main.py
sqlmesh_enterprise-0.0.1.dist-info/METADATA
sqlmesh_enterprise-0.0.1.dist-info/WHEEL
sqlmesh_enterprise-0.0.1.dist-info/entry_points.txt
sqlmesh_enterprise-0.0.1.dist-info/namespace_packages.txt
sqlmesh_enterprise-0.0.1.dist-info/top_level.txt
sqlmesh_enterprise-0.0.1.dist-info/RECORD
