Metadata-Version: 2.4
Name: sqlmesh-enterprise
Version: 0.0.1
Author: TobikoData Inc.
Author-email: engineering@tobikodata.com
Requires-Python: <3.13,>=3.9
Dynamic: author
Dynamic: author-email
Dynamic: description
Dynamic: description-content-type
Dynamic: requires-python
